geo_relations/__init__.py
geo_relations/collectors.py
geo_relations/generators.py
geo_relations/utilities.py
geo_relations/.ipynb_checkpoints/__init__-checkpoint.py
geo_relations/.ipynb_checkpoints/collectors-checkpoint.py
geo_relations/.ipynb_checkpoints/generators-checkpoint.py
geo_relations/.ipynb_checkpoints/utilities-checkpoint.py
geo_relations-1.0.2.dist-info/licenses/LICENSE
geo_relations-1.0.2.dist-info/WHEEL
geo_relations-1.0.2.dist-info/METADATA
geo_relations-1.0.2.dist-info/RECORD
