Metadata-Version: 2.4
Name: geo-relations
Version: 1.0.2
Summary: Gernerate geospatial shape pairs with prescribed relations
Keywords: geospatial,machine learning,datasets
Author-email: John Collins <john@odyssey-geospatial.com>
License-File: LICENSE
Requires-Dist: shapely
Requires-Dist: osmnx
Requires-Dist: geopandas
